py2c/__init__.py
py2c/c_to_py_code.py
py2c/py_to_c_code.py
py2c-0.0.4.dist-info/LICENSE
py2c-0.0.4.dist-info/METADATA
py2c-0.0.4.dist-info/WHEEL
py2c-0.0.4.dist-info/top_level.txt
py2c-0.0.4.dist-info/RECORD
