Metadata-Version: 2.1
Name: py2c
Version: 0.0.4
Summary: Tools to bridge python and C
Home-page: https://github.com/i2mint/py2c
License: mit
Platform: any
License-File: LICENSE
Requires-Dist: pycparser
